hamcc/__init__.py
hamcc/__main__.py
hamcc/__version__.py
hamcc/_console_.py
hamcc/hamcc.py
hamcc/data/bands.json
hamcc/data/modes.json
hamcc-1.0.dist-info/METADATA
hamcc-1.0.dist-info/WHEEL
hamcc-1.0.dist-info/entry_points.txt
hamcc-1.0.dist-info/top_level.txt
hamcc-1.0.dist-info/RECORD
