Metadata-Version: 2.4
Name: HamCC
Version: 1.0
Summary: Log Ham Radio QSOs via console
Author-email: "Andreas Schawo, DF1ASC" <andreas@schawo.de>
Project-URL: Homepage, https://github.com/gitandy/HamCC
Project-URL: Bug Tracker, https://github.com/gitandy/HamCC/issues
Classifier: Development Status :: 4 - Beta
Classifier: Intended Audience :: Developers
Classifier: Intended Audience :: End Users/Desktop
Classifier: Environment :: Console
Classifier: Operating System :: OS Independent
Classifier: Programming Language :: Python :: 3 :: Only
Classifier: Programming Language :: Python :: 3.10
Classifier: Programming Language :: Python :: 3.11
Classifier: Programming Language :: Python :: 3.12
Classifier: Topic :: Communications :: Ham Radio
Classifier: Topic :: Software Development :: Libraries
Classifier: Topic :: Software Development :: Libraries :: Python Modules
Requires-Python: >=3.10
Requires-Dist: PyADIF-File~=1.3
Requires-Dist: windows-curses; os_name == "nt"
